{
  "airports": [
    {
      "elevationFt": 14.0,
      "ident": "0W0",
      "latitudeDeg": 47.632212,
      "longitudeDeg": -122.327653,
      "name": "Seattle Seaplanes Seaplane Base",
      "positionENU": [
        1675.8291015625,
        4.267199993133545,
        -1980.151123046875
      ],
      "type": "seaplane_base"
    },
    {
      "elevationFt": 21.0,
      "ident": "KBFI",
      "latitudeDeg": 47.529999,
      "longitudeDeg": -122.302002,
      "name": "Boeing Field King County International Airport",
      "positionENU": [
        3599.42919921875,
        6.4008002281188965,
        -13358.4501953125
      ],
      "type": "medium_airport"
    },
    {
      "elevationFt": 14.0,
      "ident": "S60",
      "latitudeDeg": 47.754799,
      "longitudeDeg": -122.259003,
      "name": "Kenmore Air Harbor LLC Seaplane Base",
      "positionENU": [
        6823.97705078125,
        4.267199993133545,
        11666.1708984375
      ],
      "type": "seaplane_base"
    },
    {
      "elevationFt": 14.0,
      "ident": "US-0943",
      "latitudeDeg": 47.66,
      "longitudeDeg": -122.21,
      "name": "Seaplane Scenics at Carillon Point Seaplane Base",
      "positionENU": [
        10498.7724609375,
        4.267199993133545,
        1113.1949462890625
      ],
      "type": "seaplane_base"
    },
    {
      "elevationFt": 6.0,
      "ident": "US-12381",
      "latitudeDeg": 47.522598,
      "longitudeDeg": -122.305,
      "name": "Boeing Military Airplanes Heliport",
      "positionENU": [
        3374.60546875,
        1.8287999629974365,
        -14182.326171875
      ],
      "type": "closed"
    },
    {
      "elevationFt": 120.0,
      "ident": "US-12410",
      "latitudeDeg": 47.621226,
      "longitudeDeg": -122.343226,
      "name": "Seattle Private Number One Heliport",
      "positionENU": [
        507.9906005859375,
        36.57600021362305,
        -3203.10693359375
      ],
      "type": "closed"
    },
    {
      "elevationFt": 52.0,
      "ident": "US-12414",
      "latitudeDeg": 47.651626,
      "longitudeDeg": -122.323366,
      "name": "Lake Union Heliport",
      "positionENU": [
        1997.3165283203125,
        15.849599838256836,
        181.0054931640625
      ],
      "type": "closed"
    },
    {
      "elevationFt": 33.0,
      "ident": "US-6084",
      "latitudeDeg": 47.68164,
      "longitudeDeg": -122.25347,
      "name": "Naval Air Station Seattle",
      "positionENU": [
        7238.90380859375,
        10.05840015411377,
        3522.148681640625
      ],
      "type": "closed"
    },
    {
      "elevationFt": 2.0,
      "ident": "US-9430",
      "latitudeDeg": 47.574198,
      "longitudeDeg": -122.548488,
      "name": "Manchester Laboratory Heliport",
      "positionENU": [
        -14884.859375,
        0.6096000075340271,
        -8438.240234375
      ],
      "type": "closed"
    },
    {
      "elevationFt": 14.0,
      "ident": "W55",
      "latitudeDeg": 47.629002,
      "longitudeDeg": -122.338997,
      "name": "Kenmore Air Harbor Seaplane Base",
      "positionENU": [
        825.1285400390625,
        4.267199993133545,
        -2337.486572265625
      ],
      "type": "seaplane_base"
    },
    {
      "elevationFt": 50.0,
      "ident": "WA61",
      "latitudeDeg": 47.798301696777344,
      "longitudeDeg": -122.52999877929688,
      "name": "Thompson Airport",
      "positionENU": [
        -13498.330078125,
        15.239999771118164,
        16508.869140625
      ],
      "type": "small_airport"
    }
  ],
  "boundsLLA": [
    47.49999931385772,
    -122.55000071230059,
    47.800000686142276,
    -122.1499992876994
  ],
  "originLLA": [
    47.65,
    -122.35,
    0.0
  ],
  "runways": [
    {
      "airportIdent": "KBFI",
      "closed": "0",
      "heENU": [
        3749.332763671875,
        6.4008002281188965,
        -13447.2265625
      ],
      "heElevationFt": 21.0,
      "heIdent": "32R",
      "heLatitudeDeg": 47.52920150756836,
      "heLongitudeDeg": -122.30000305175781,
      "leENU": [
        3224.6826171875,
        6.4008002281188965,
        -12467.9833984375
      ],
      "leElevationFt": 21.0,
      "leIdent": "14L",
      "leLatitudeDeg": 47.53799819946289,
      "leLongitudeDeg": -122.30699920654297,
      "lengthFt": "3709",
      "lighted": "1",
      "surface": "ASP",
      "widthFt": "100"
    },
    {
      "airportIdent": "KBFI",
      "closed": "0",
      "heENU": [
        4424.455078125,
        6.4008002281188965,
        -14827.7646484375
      ],
      "heElevationFt": 21.0,
      "heIdent": "32L",
      "heLatitudeDeg": 47.51679992675781,
      "heLongitudeDeg": -122.29100036621094,
      "leENU": [
        2924.88232421875,
        5.181600093841553,
        -12189.4130859375
      ],
      "leElevationFt": 17.0,
      "leIdent": "14R",
      "leLatitudeDeg": 47.54050064086914,
      "leLongitudeDeg": -122.31099700927734,
      "lengthFt": "10007",
      "lighted": "1",
      "surface": "ASP",
      "widthFt": "200"
    }
  ]
}
